hive/common/__init__.py
hive/common/__version__.py
hive/common/argument_parser.py
hive/common/config.py
hive/common/datetime.py
hive/common/dictutil.py
hive/common/endpoint_config.py
hive/common/httpx.py
hive/common/langchain.py
hive/common/logging.py
hive/common/ollama.py
hive/common/py.typed
hive/common/resource.py
hive/common/service_name.py
hive/common/socketserver.py
hive/common/testing.py
hive/common/typing.py
hive/common/units.py
hive/common/uuid.py
hive/common/xdg.py
hive_common-0.4.3.dist-info/METADATA
hive_common-0.4.3.dist-info/WHEEL
hive_common-0.4.3.dist-info/top_level.txt
hive_common-0.4.3.dist-info/RECORD
